{
	"settings": {
		"index.number_of_replicas": 1,
		"index.number_of_shards": 5
	},
	"mappings": {
		"job": {
			"_source": {
				"compress": true
			},
			"dynamic_templates": [
				{
					"default_ids": {
						"mapping": {
							"index": "not_analyzed",
							"type": "string",
							"doc_values": true
						},
						"match": "id"
					}
				},
				{
					"default_strings": {
						"mapping": {
							"index": "not_analyzed",
							"type": "string",
							"doc_values": true
						},
						"match_mapping_type": "string",
						"match": "*"
					}
				},
				{
					"default_doubles": {
						"mapping": {
							"index": "not_analyzed",
							"type": "double",
							"doc_values": true
						},
						"match_mapping_type": "double",
						"match": "*"
					}
				},
				{
					"default_longs": {
						"mapping": {
							"index": "not_analyzed",
							"type": "long",
							"doc_values": true
						},
						"match_mapping_type": "long|integer",
						"match_pattern": "regex",
						"path_match": ".*"
					}
				}
			],
			"properties": {
				"action":{
					"type": "object",
					"dynamic": true,
					"properties":{
						"timings":{
							"type":"nested",
							"dynamic": true
						}
					}
				},
				"properties": {
					"type":"object",
					"dynamic": true
				},
				"other": {
					"type": "nested",
					"dynamic": false,
					"properties": {
						"name": {
							"type": "string",
							"index": "not_analyzed",
							"doc_values": true
						},
						"value": {
							"type": "string",
							"index": "not_analyzed",
							"doc_values": true
						}
					}
				},
				"etl": {
					"type": "object",
					"properties": {
						"id": {
							"type": "integer",
							"doc_values": true
						},
						"source": {
							"type": "object",
							"properties": {
								"id": {
									"type": "integer",
									"doc_values": true
								},
								"source": {
									"type": "object",
									"properties": {
										"id": {
											"type": "integer",
											"doc_values": true
										},
										"source": {
											"type": "object",
											"properties": {
												"id": {
													"type": "integer",
													"doc_values": true
												}
											}
										}
									}
								}

							}
						}

					}
				}
			},
			"_all": {
				"enabled": false
			}
		}
	}

}
